pyparrotsay.py
PyParrotSay-1.0.3.data/scripts/pyparrotsay.py
PyParrotSay-1.0.3.dist-info/METADATA
PyParrotSay-1.0.3.dist-info/WHEEL
PyParrotSay-1.0.3.dist-info/top_level.txt
PyParrotSay-1.0.3.dist-info/RECORD
