Metadata-Version: 2.1
Name: PyParrotSay
Version: 1.0.3
Home-page: https://github.com/DevHollo/pyparrotsay
Author: Hollo
Author-email: hollo1234567890e@gmail.com
Requires-Dist: sty ==1.0.6
